discordtownlistpy/__init__.py
discordtownlistpy-0.0.3.dist-info/LICENSE
discordtownlistpy-0.0.3.dist-info/METADATA
discordtownlistpy-0.0.3.dist-info/WHEEL
discordtownlistpy-0.0.3.dist-info/top_level.txt
discordtownlistpy-0.0.3.dist-info/RECORD
